steam/__init__.py
steam/enums.py
steam/globalid.py
steam/guard.py
steam/steamid.py
steam/webapi.py
steam/webauth.py
steam/client/__init__.py
steam/client/gc.py
steam/client/user.py
steam/client/builtins/__init__.py
steam/client/builtins/account.py
steam/client/builtins/apps.py
steam/client/builtins/friends.py
steam/client/builtins/gameservers.py
steam/client/builtins/leaderboards.py
steam/client/builtins/misc.py
steam/client/builtins/unified_messages.py
steam/client/builtins/user.py
steam/client/builtins/web.py
steam/client/features/__init__.py
steam/client/features/misc.py
steam/client/features/user.py
steam/client/features/web.py
steam/client/mixins/__init__.py
steam/client/mixins/friends.py
steam/core/__init__.py
steam/core/cm.py
steam/core/connection.py
steam/core/crypto.py
steam/core/msg.py
steam/core/msg/__init__.py
steam/core/msg/headers.py
steam/core/msg/structs.py
steam/core/msg/unified.py
steam/enums/__init__.py
steam/enums/base.py
steam/enums/common.py
steam/enums/emsg.py
steam/protobufs/__init__.py
steam/protobufs/content_manifest_pb2.py
steam/protobufs/encrypted_app_ticket_pb2.py
steam/protobufs/gc_pb2.py
steam/protobufs/steammessages_base_pb2.py
steam/protobufs/steammessages_broadcast_pb2.py
steam/protobufs/steammessages_clientserver_2_pb2.py
steam/protobufs/steammessages_clientserver_pb2.py
steam/protobufs/steammessages_cloud_pb2.py
steam/protobufs/steammessages_credentials_pb2.py
steam/protobufs/steammessages_depotbuilder_pb2.py
steam/protobufs/steammessages_deviceauth_pb2.py
steam/protobufs/steammessages_econ_pb2.py
steam/protobufs/steammessages_gamenotifications_pb2.py
steam/protobufs/steammessages_gameservers_pb2.py
steam/protobufs/steammessages_inventory_pb2.py
steam/protobufs/steammessages_linkfilter_pb2.py
steam/protobufs/steammessages_offline_pb2.py
steam/protobufs/steammessages_parental_pb2.py
steam/protobufs/steammessages_partnerapps_pb2.py
steam-0.8.14.dist-info/DESCRIPTION.rst
steam-0.8.14.dist-info/METADATA
steam-0.8.14.dist-info/RECORD
steam-0.8.14.dist-info/WHEEL
steam-0.8.14.dist-info/metadata.json
steam-0.8.14.dist-info/top_level.txt
steam-0.8.14.dist-info/zip-safe
