Metadata-Version: 2.0
Name: steam
Version: 0.8.14
Summary: Module for interacting with various Steam features
Home-page: https://github.com/ValvePython/steam
Author: Rossen Georgiev
Author-email: rossen@rgp.io
License: MIT
Keywords: valve steam steamid api webapi steamcommunity
Platform: UNKNOWN
Classifier: Development Status :: 4 - Beta
Classifier: Natural Language :: English
Classifier: Intended Audience :: Developers
Classifier: License :: OSI Approved :: MIT License
Classifier: Operating System :: OS Independent
Classifier: Programming Language :: Python :: 2.7
Classifier: Programming Language :: Python :: 3.3
Classifier: Programming Language :: Python :: 3.4
Classifier: Programming Language :: Python :: 3.5
Requires-Dist: cryptography (>=1.3)
Requires-Dist: enum34 (>=1.0.4)
Requires-Dist: requests (>=2.9.1)
Requires-Dist: six (>=1.10)
Requires-Dist: vdf (>=2.0)
Provides-Extra: client
Requires-Dist: gevent (>=1.1.0); extra == 'client'
Requires-Dist: gevent-eventemitter (>=2.0); extra == 'client'
Requires-Dist: protobuf (>=3.0.0); extra == 'client'
